{
    "appName": "Gallery App",
    "tagline": "gallery App Tagline",
    "keywords": ["keyword1", "keyword2", "keyword3"],
    "brandLogo": "path/to/gallery/logo.png",
    "metaDescription": "gallery App Meta Description",
    "author": "Author Name",
    "contactEmail": "contact@galleryapp.com",
    "socialMedia": {
        "facebook": "https://www.facebook.com/galleryapp",
        "twitter": "https://twitter.com/galleryapp",
        "instagram": "https://www.instagram.com/galleryapp",
        "linkedin": "https://www.linkedin.com/company/galleryapp"
    },
    "analytics": {
        "googleAnalyticsID": "gallery Google Analytics ID",
        "facebookPixelID": "gallery Facebook Pixel ID"
    },
    "themeColor": "#000000",
    "backgroundColor": "#ffffff",
    "serverPort": 3000,
    "database": {
        "url": "gallery Database URL",
        "name": "gallery Database Name"
    },
    "seo": {
        "titleTemplate": "%s - Gallery App",
        "defaultTitle": "Gallery App",
        "description": "gallery App Description",
        "canonical": "https://www.galleryapp.com",
        "openGraph": {
            "url": "https://www.galleryapp.com",
            "title": "Gallery App",
            "description": "gallery App Description",
            "images": [
                {
                    "url": "https://www.galleryapp.com/static/images/og-image.jpg",
                    "width": 800,
                    "height": 600,
                    "alt": "Gallery App"
                }
            ],
            "site_name": "Gallery App"
        },
        "twitter": {
            "handle": "@galleryapp",
            "cardType": "summary_large_image"
        }
    },
    "content" : {
        "tagline" :"gallery App Tagline",
        "features": [
            {
                "title": "Feature 1",
                "description": "Feature 1 Description",
                "icon": "path/to/feature1-icon.png"
            },
            {
                "title": "Feature 2",
                "description": "Feature 2 Description",
                "icon": "path/to/feature2-icon.png"
            },
            {
                "title": "Feature 3",
                "description": "Feature 3 Description",
                "icon": "path/to/feature3-icon.png"
            }
        ]
    }
}